restclient/restclient.py
dig_us_up_restclient-0.1.0.dist-info/METADATA
dig_us_up_restclient-0.1.0.dist-info/WHEEL
dig_us_up_restclient-0.1.0.dist-info/RECORD
